dajare/__init__.py
dajare/crawler.py
dajare/crawler_biwa_ne_jp.py
dajare/crawler_dajare_jp.py
dajare/crawler_dajare_net.py
dajare/crawler_dajarenavi_net.py
dajare/crawler_dajareshuu_web.py
dajare/crawler_kaishaseikatsu_jp.py
dajare/crawler_syuukaizyo_web.py
dajare/dajare_search.py
dajare-0.0.1.dist-info/METADATA
dajare-0.0.1.dist-info/WHEEL
dajare-0.0.1.dist-info/entry_points.txt
dajare-0.0.1.dist-info/top_level.txt
dajare-0.0.1.dist-info/RECORD
