Metadata-Version: 2.1
Name: dajare
Version: 0.0.1
Summary: dajare search
Home-page: https://github.com/vaaaaanquish/dajare-python
Author: vaaaaanquish
Author-email: 6syun9@gmail.com
License: MIT
Platform: any
Requires-Dist: beautifulsoup4
Requires-Dist: requests
Requires-Dist: requests-cache
Requires-Dist: tqdm
